d3_titanic_workshop/__init__.py
d3_titanic_workshop/data.py
d3_titanic_workshop/epic_leaderboard.py
d3_titanic_workshop/score.py
d3_titanic_workshop/res/checking_data.pkl
d3_titanic_workshop/res/family_info.csv
d3_titanic_workshop/res/passengers.csv
d3_titanic_workshop/res/test_family_info.csv
d3_titanic_workshop/res/test_passengers.csv
d3_titanic_workshop/res/test_tickets.csv
d3_titanic_workshop/res/tickets.csv
d3_titanic_workshop-0.1.1.dist-info/LICENSE
d3_titanic_workshop-0.1.1.dist-info/METADATA
d3_titanic_workshop-0.1.1.dist-info/WHEEL
d3_titanic_workshop-0.1.1.dist-info/top_level.txt
d3_titanic_workshop-0.1.1.dist-info/RECORD
