Metadata-Version: 2.1
Name: d3-titanic-workshop
Version: 0.1.1
Summary: Helper functions for the D3 Titanic Data Engineering Workshop
Home-page: http://epicleaderboard.com/app.html#/detail/8c5a12fc290fe521b2aea4efdf9bed97
Author: Ryan McKeown
Author-email: ryanmckeown@mail4me.com
License: UNKNOWN
Platform: UNKNOWN
Classifier: Programming Language :: Python :: 3
Classifier: License :: OSI Approved :: MIT License
Classifier: Operating System :: OS Independent
Requires-Python: >=3.4
Requires-Dist: requests
Requires-Dist: pandas
